valconfig/__init__.py
valconfig/_version.py
valconfig/valconfig.py
valconfig/contrib/README.md
valconfig/contrib/holoviews.py
valconfig/contrib/paul_tol_colors.cfg
valconfig-0.1.2.dist-info/LICENSE
valconfig-0.1.2.dist-info/METADATA
valconfig-0.1.2.dist-info/WHEEL
valconfig-0.1.2.dist-info/top_level.txt
valconfig-0.1.2.dist-info/RECORD
