Metadata-Version: 2.1
Name: valconfig
Version: 0.1.2
Summary: Simple, extendable configuration files, using Pydantic for validation.
Author-email: Alexandre René <alex.c.rene@gmail.com>
License: MPL 2.0
Project-URL: Documentation, https://validating-config.readthedocs.io/
Project-URL: Source, https://github.com/alcrene/valconfig
Project-URL: Bug Tracker, https://github.com/alcrene/valconfig/issues
Keywords: config,configuration,validation,hierarchical,scientific computing,reproducibility
Classifier: Development Status :: 4 - Beta
Classifier: License :: OSI Approved :: Mozilla Public License 2.0 (MPL 2.0)
Classifier: Intended Audience :: Developers
Classifier: Intended Audience :: Science/Research
Classifier: Programming Language :: Python :: 3
Classifier: Programming Language :: Python :: 3 :: Only
Classifier: Programming Language :: Python :: 3.8
Classifier: Programming Language :: Python :: 3.9
Classifier: Programming Language :: Python :: 3.10
Classifier: Programming Language :: Python :: 3.11
Classifier: Topic :: Scientific/Engineering
Classifier: Topic :: Software Development :: Libraries
Classifier: Topic :: Utilities
Classifier: Typing :: Typed
Requires-Python: >=3.8
License-File: LICENSE
Requires-Dist: pydantic
Requires-Dist: addict
Provides-Extra: docs
Requires-Dist: sphinx ; extra == 'docs'
Requires-Dist: myst-parser ; extra == 'docs'
Requires-Dist: sphinx-book-theme ; extra == 'docs'
Requires-Dist: sphinx-design ; extra == 'docs'
Provides-Extra: test
Requires-Dist: pytest ; extra == 'test'
